paymentsoslib/__init__.py
paymentsoslib/paymentsos.py
paymentsoslib-0.0.2.dist-info/licenses/LICENSE
paymentsoslib-0.0.2.dist-info/METADATA
paymentsoslib-0.0.2.dist-info/WHEEL
paymentsoslib-0.0.2.dist-info/top_level.txt
paymentsoslib-0.0.2.dist-info/RECORD
