Metadata-Version: 2.4
Name: paymentsoslib
Version: 0.0.2
Summary: A lightweight Python client for PaymentsOS Management and Reporting APIs.
Author: Fabio Soares
Author-email: Paulo Portela <portela.paulo@gmail.com>
Maintainer: Fabio Soares
Maintainer-email: Paulo Portela <portela.paulo@gmail.com>
License-Expression: BSD-3-Clause
Project-URL: Homepage, https://github.com/aghuttun/paymentsoslib
Project-URL: Documentation, https://github.com/aghuttun/paymentsoslib/blob/main/README.md
Keywords: payments,paymentsos,reporting,api,client
Classifier: Topic :: Software Development :: Libraries
Classifier: Programming Language :: Python :: 3
Classifier: Programming Language :: Python :: 3 :: Only
Classifier: Programming Language :: Python :: 3.9
Classifier: Programming Language :: Python :: 3.10
Classifier: Programming Language :: Python :: 3.11
Classifier: Programming Language :: Python :: 3.12
Classifier: Programming Language :: Python :: 3.13
Classifier: Programming Language :: Python :: 3.14
Classifier: Intended Audience :: Developers
Classifier: Operating System :: OS Independent
Requires-Python: >=3.10
License-File: LICENSE
Requires-Dist: requests>=2.31
Provides-Extra: dev
Requires-Dist: twine; extra == "dev"
Requires-Dist: build; extra == "dev"
Dynamic: license-file
